shared_atomic/__init__.py
shared_atomic/atomic_activation.pyi
shared_atomic/atomic_async_activation_check.pyi
shared_atomic/atomic_boolfloat.pyi
shared_atomic/atomic_bytearray.pyi
shared_atomic/atomic_int.pyi
shared_atomic/atomic_object_backend.pyi
shared_atomic/atomic_shared_memory.pyi
shared_atomic/atomic_tools.py
shared_atomic/atomic_tools.pyi
shared_atomic/atomic_uint.pyi
shared_atomic/end_user_license_agreement.txt
shared_atomic/shared_dict.pyi
shared_atomic/test_atomic_array.py
shared_atomic/test_atomic_boolfloat.py
shared_atomic/test_atomic_int.py
shared_atomic/test_atomic_shared_memory.py
shared_atomic/test_atomic_uint.py
shared_atomic/test_core_dump.py
shared_atomic/test_shared_dict.arm64.py
shared_atomic/test_shared_dict.py
shared_atomic/urwid_win_patch.py
shared_atomic_enterprise-5!4.2.2.dist-info/METADATA
shared_atomic_enterprise-5!4.2.2.dist-info/WHEEL
shared_atomic_enterprise-5!4.2.2.dist-info/top_level.txt
shared_atomic_enterprise-5!4.2.2.dist-info/RECORD
