Metadata-Version: 2.1
Name: shared_atomic_enterprise
Version: 5!4.2.2
Summary: Concurrent Python utils and data types
Home-page: https://sharedatomic.top/
Author: Xiquan Ren
Author-email: xiquanren@yandex.com
Requires-Python: >=3.7, <3.13
Requires-Dist: urwid
Requires-Dist: windows-curses ; platform_system == "Windows"
